deplyai_cli-0.4.2.data/scripts/deply
src/__init__.py
src/auth.py
src/cmd.py
src/pipelines.py
src/util.py
deplyai_cli-0.4.2.dist-info/LICENSE
deplyai_cli-0.4.2.dist-info/METADATA
deplyai_cli-0.4.2.dist-info/WHEEL
deplyai_cli-0.4.2.dist-info/top_level.txt
deplyai_cli-0.4.2.dist-info/RECORD
