Metadata-Version: 2.1
Name: deplyai-cli
Version: 0.4.2
Summary: Command Line Environment for DeplyAI's integrated AI agent platform.
Maintainer: DeplyAI
Maintainer-email: support@deplyai.com
License: BSD-3-Clause
Project-URL: Bug Tracker, https://github.com/deply-ai/cli/issues
Project-URL: Documentation, https://github.com/deply-ai/cli
Project-URL: Source Code, https://github.com/deply-ai/cli
Keywords: deplyai
Platform: Linux
Platform: Windows
Platform: MacOS
Classifier: Development Status :: 3 - Alpha
Classifier: Environment :: Console
Classifier: Intended Audience :: Developers
Classifier: Intended Audience :: System Administrators
Classifier: Natural Language :: English
Classifier: License :: OSI Approved :: BSD License
Classifier: Programming Language :: Python
Classifier: Programming Language :: Python :: 3
Classifier: Programming Language :: Python :: 3 :: Only
Classifier: Programming Language :: Python :: 3.10
Classifier: Programming Language :: Python :: 3.11
Classifier: Programming Language :: Python :: 3.12
Requires-Python: >= 3.10
License-File: LICENSE
Requires-Dist: deplyai ==0.1.2
Requires-Dist: requests
